LICENSE.txt
README.rst
setup.py
EcgBenchmark_toolkit/__init__.py
EcgBenchmark_toolkit.egg-info/PKG-INFO
EcgBenchmark_toolkit.egg-info/SOURCES.txt
EcgBenchmark_toolkit.egg-info/dependency_links.txt
EcgBenchmark_toolkit.egg-info/top_level.txt
EcgBenchmark_toolkit/benchmark/__init__.py
EcgBenchmark_toolkit/benchmark/A+N/__init__.py
EcgBenchmark_toolkit/benchmark/CD+N/__init__.py
EcgBenchmark_toolkit/benchmark/HYP+N/__init__.py
EcgBenchmark_toolkit/benchmark/MI+N/__init__.py
EcgBenchmark_toolkit/benchmark/S+N/__init__.py
EcgBenchmark_toolkit/benchmark/V+N/__init__.py
EcgBenchmark_toolkit/methods/Plotting.py
EcgBenchmark_toolkit/methods/Test.py
EcgBenchmark_toolkit/methods/__init__.py
EcgBenchmark_toolkit/methods/loading_benchmark.py
EcgBenchmark_toolkit/methods/DL/CNN.py
EcgBenchmark_toolkit/methods/DL/DNN.py
EcgBenchmark_toolkit/methods/DL/LSTM.py
EcgBenchmark_toolkit/methods/DL/MLP.py
EcgBenchmark_toolkit/methods/DL/__init__.py
EcgBenchmark_toolkit/processing/__init__.py
EcgBenchmark_toolkit/processing/denoising.py
EcgBenchmark_toolkit/processing/preprocessing.py